{
  "kind": "hdo#vote",
  "externalId": "2011-06-07 17:33:26.150j",
  "externalIssueId": "50264",
  "counts": {
    "for": 0,
    "against": 0,
    "absent": 0
  },
  "personal": false,
  "enacted": true,
  "subject": "Romertall I til og med IV er opptatt.",
  "method": "ikke_spesifisert",
  "resultType": "ikke_spesifisert",
  "time": "2011-06-07 17:33:26 +0200",
  "representatives": [

  ],
  "propositions": [
    {
      "kind": "hdo#proposition",
      "externalId": "2011-06-07 17:33:26 +0200:1759",
      "description": "Komiteens tilråding",
      "onBehalfOf": "",
      "body": "om endringar i straffeprosesslova mv. \n(etterforskingsplikt mv.)<p><b>I</b></p><p><b>I lov 22. mai 1902 nr. 10 Almindelig borgerlig\nStraffelov § 219 skal bokstav a og b i første ledd lyde:</b></p><p>a) \tsin tidligere eller nåværende ektefelle <em>eller\nsamboer</em>,</p><p>b) \tsin eller tidligere eller nåværende ektefelles eller samboers\nslektning i rett nedstigende linje,</p><p><b>II</b></p><p><b>I lov 22. mai 1981 nr. 25 om rettergangsmåten\ni straffesaker § 224 fjerde ledd skal nytt andre punktum lyde:</b></p><p><em>Det samme gjelder når barn under 18 år dør plutselig\nog uventet.</em></p><p><b>III</b></p><p><b>I lov 20. mai 2005 nr. 28 om straff skal\n§ 282 bokstav a og b lyde:</b></p><p>sin nåværende eller tidligere ektefelle <em>eller\nsamboer</em>,</p><p>sin eller nåværende eller tidligere ektefelles <em>eller samboers</em> slektning\ni rett nedstigende linje,</p><p><b>IV</b></p><p>1.\tDel I og III trer i kraft straks.</p><p>2.\tDel II gjeld frå den tida Kongen fastset.</p>"
    }
  ],
  "propositionsMissing": null
}