{
  "kind": "hdo#vote",
  "externalId": "1269518582e",
  "externalIssueId": "44391",
  "counts": {
    "for": 0,
    "against": 0,
    "absent": 0
  },
  "personal": false,
  "enacted": true,
  "subject": "Komiteens tilråding",
  "time": "2010-03-25 13:03:02 +0100",
  "propositions": [
    {
      "kind": "hdo#proposition",
      "description": "Komiteens tilråding",
      "body": "<FONT SIZE=2>\n<div class=Section1>\n<p class=brodtekstminnr style='text-indent:0cm'><span style='mso-font-width:\n100%'>Dokument 8:4 S (2009-2010) - representantforslag fra Abid Q. Raja og\nTrine Skei Grande om forsterket innsats mot frafall i skolen - vedlegges\nprotokollen.<o:p></o:p></span><BR>\n<p class=MsoNormal><o:p>&nbsp;</o:p><BR>\n</div>\n</FONT>",
      "externalId": "63:2:219",
      "onBehalfOf": "",
      "editing": false,
      "metadata": {
        "status": "approved",
        "username": "Hanna"
      }
    }
  ]
}